oarepo_heartbeat_common/__init__.py
oarepo_heartbeat_common/checks.py
oarepo_heartbeat_common/cli.py
oarepo_heartbeat_common/errors.py
oarepo_heartbeat_common/ext.py
oarepo_heartbeat_common/version.py
oarepo_heartbeat_common-1.0.9.dist-info/AUTHORS.rst
oarepo_heartbeat_common-1.0.9.dist-info/LICENSE
oarepo_heartbeat_common-1.0.9.dist-info/METADATA
oarepo_heartbeat_common-1.0.9.dist-info/WHEEL
oarepo_heartbeat_common-1.0.9.dist-info/entry_points.txt
oarepo_heartbeat_common-1.0.9.dist-info/top_level.txt
oarepo_heartbeat_common-1.0.9.dist-info/RECORD
